README.md
setup.py
trapmk/__init__.py
trapmk/trapmk.py
trapmk.egg-info/PKG-INFO
trapmk.egg-info/SOURCES.txt
trapmk.egg-info/dependency_links.txt
trapmk.egg-info/entry_points.txt
trapmk.egg-info/requires.txt
trapmk.egg-info/top_level.txt