Metadata-Version: 1.0
Name: trapmk
Version: 0.6.0
Summary: trapmk: TrapHack adventure builder
Home-page: UNKNOWN
Author: SlimeMaid
Author-email: slimemaid@gmail.com
License: UNKNOWN
Keywords: cli
Platform: UNKNOWN
